BotCore
