Metadata-Version: 2.1
Name: BotCore
Version: 1.1.4
Summary: Base core for telegram bots.
Home-page: https://gitlab.com/Tullp/botcore
Author: Maks Vinnytskyi
Author-email: ownerofforest@gmail.com
License: MIT
Platform: UNKNOWN
License-File: license.txt
